{
  "task_name": "llama3.1_8b_lora_training_tp2_supplement",
  "model_name": "Meta-Llama-3.1-8B",
  "model_path": "/home/o_mabin/clj-proj/model/Meta-Llama-3.1-8B",
  "training_mode": "lora",
  "sequence_length": 4096,
  "global_batch_size": 16,
  "micro_batch_size": 2,
  "gradient_accumulation_steps": 4,
  "optimizer": "adamw",
  "learning_rate": 0.0002,
  "precision": "fp16",
  "zero_stage": 1,
  "activation_checkpointing": true,
  "parallelism": {
    "data_parallel_size": 2,
    "pipeline_parallel_size": 1,
    "tensor_parallel_size": 2
  },
  "dataset": {
    "name": "instruction_sft_sample",
    "format": "jsonl",
    "shards": 8
  }
}